conding/__init__.py
conding/_modidx.py
conding/dune/__init__.py
conding/dune/dune.py
conding/dune/tec.py
conding/pamm/__init__.py
conding/pamm/abc.py
conding/pamm/bancor.py
conding/samm/__init__.py
conding/samm/uniswap.py
conding/utils/__init__.py
conding/utils/formatted_param.py
conding-0.1.3.dist-info/LICENSE
conding-0.1.3.dist-info/METADATA
conding-0.1.3.dist-info/WHEEL
conding-0.1.3.dist-info/entry_points.txt
conding-0.1.3.dist-info/top_level.txt
conding-0.1.3.dist-info/RECORD
