Metadata-Version: 2.1
Name: conding
Version: 0.1.3
Summary: Python library for analysing and modelling bonding curves. This library is managed using nbdev with application development in python param panel.
Home-page: https://github.com/bonding-curves/conding
Author: Shawn Anderson
Author-email: shawn@longtailfinancial.com
License: Apache Software License 2.0
Keywords: nbdev jupyter notebook python
Classifier: Development Status :: 4 - Beta
Classifier: Intended Audience :: Developers
Classifier: Natural Language :: English
Classifier: Programming Language :: Python :: 3.7
Classifier: Programming Language :: Python :: 3.8
Classifier: Programming Language :: Python :: 3.9
Classifier: Programming Language :: Python :: 3.10
Classifier: License :: OSI Approved :: Apache Software License
Requires-Python: >=3.7
License-File: LICENSE
Requires-Dist: pandas (>=1.5.3)
Requires-Dist: hvplot (>=0.8.3)
Requires-Dist: python-dotenv (>=1.0.0)
Requires-Dist: dune-client (>=1.0.0)
Requires-Dist: diskcache (>=5.6.1)
Requires-Dist: pyparsing (>=3.0.9)
Requires-Dist: yfinance (>=0.2.18)
Provides-Extra: dev
Requires-Dist: nbdev (>=2.3.12) ; extra == 'dev'
Requires-Dist: jupyterlab (==3.6.0) ; extra == 'dev'
Requires-Dist: ipython (>=8.12.0) ; extra == 'dev'
Requires-Dist: icecream (>=2.1.3) ; extra == 'dev'
